minicons/__init__.py
minicons/bin/__init__.py
minicons/bin/score_cli.py
minicons/bin/sentence_score_cli.py
minicons/cwe.py
minicons/scorer.py
minicons/supervised.py
minicons/utils.py
minicons-0.3.35.dist-info/LICENSE
minicons-0.3.35.dist-info/METADATA
minicons-0.3.35.dist-info/WHEEL
minicons-0.3.35.dist-info/entry_points.txt
minicons-0.3.35.dist-info/RECORD
