Metadata-Version: 2.1
Name: minicons
Version: 0.3.35
Summary: A package of useful functions to analyze transformer based language models.
Home-page: https://github.com/kanishkamisra/minicons
License: MIT
Keywords: transformers,language models,nlp,interpretability
Author: Kanishka Misra
Author-email: kanishka.replies@gmail.com
Requires-Python: >=3.9.0,<4
Classifier: License :: OSI Approved :: MIT License
Classifier: Programming Language :: Python :: 3
Classifier: Programming Language :: Python :: 3.9
Classifier: Programming Language :: Python :: 3.10
Classifier: Programming Language :: Python :: 3.11
Requires-Dist: accelerate (>=0.25.0)
Requires-Dist: numpy (>=2.0.0)
Requires-Dist: pandas (>=2.2.0)
Requires-Dist: pillow (>=10.2.0)
Requires-Dist: tenacity (>=8.2.3)
Requires-Dist: torch (>=2.5.0)
Requires-Dist: transformers (>=4.53)
Requires-Dist: urllib3 (>=1.26.7,<3.0.0)
Requires-Dist: wonderwords (>=2.2.0)
Project-URL: Repository, https://github.com/kanishkamisra/minicons
